piefs/__init__.py
piefs/benchmark.py
piefs/eikonal.py
piefs/kernels.py
piefs/morphology.py
piefs-0.0.1.dist-info/LICENSE
piefs-0.0.1.dist-info/METADATA
piefs-0.0.1.dist-info/WHEEL
piefs-0.0.1.dist-info/top_level.txt
piefs-0.0.1.dist-info/RECORD
