Metadata-Version: 2.1
Name: piefs
Version: 0.0.1
Summary: Solves eikonal function on instance maps.
Home-page: https://github.com/buswinka/piefs
Author: Chris Buswinka
Author-email: buswinka@g.harvard.edu
Classifier: Programming Language :: Python :: 3
Requires-Python: >=3.10
License-File: LICENSE
Requires-Dist: torch (>=2.0.0)
Requires-Dist: triton (>=2.0.0)
